gmm_gpu/__init__.py
gmm_gpu/gmm.py
gmm_gpu-0.2.8.dist-info/LICENSE.txt
gmm_gpu-0.2.8.dist-info/METADATA
gmm_gpu-0.2.8.dist-info/WHEEL
gmm_gpu-0.2.8.dist-info/RECORD
