Metadata-Version: 2.1
Name: gmm-gpu
Version: 0.2.8
Summary: A small library for quick fitting of multiple Gaussian Mixture Models in parallel on the GPU.
License: MIT
Author: Mihail Zdravkov
Author-email: mihail0zdravkov@gmail.com
Requires-Python: >=3.9,<4.0
Classifier: License :: OSI Approved :: MIT License
Classifier: Programming Language :: Python :: 3
Classifier: Programming Language :: Python :: 3.9
Classifier: Programming Language :: Python :: 3.10
Classifier: Programming Language :: Python :: 3.11
Classifier: Programming Language :: Python :: 3.12
Classifier: Programming Language :: Python :: 3.13
Requires-Dist: numpy (>=1.26.4,<2.0.0)
Requires-Dist: torch (>=2.5.1,<3.0.0)
